bin/convert_hf_to_gguf.py
bin/ggml-metal.metal
bin/llama-llava-cli
bin/llama-minicpmv-cli
include/ggml-alloc.h
include/ggml-backend.h
include/ggml-blas.h
include/ggml-cann.h
include/ggml-cuda.h
include/ggml-kompute.h
include/ggml-metal.h
include/ggml-rpc.h
include/ggml-sycl.h
include/ggml-vulkan.h
include/ggml.h
include/llama.h
lib/cmake/llama/llama-config.cmake
lib/cmake/llama/llama-version.cmake
lib/libggml.a
lib/libggml_llama.dylib
lib/libllama.dylib
lib/libllava.dylib
lib/pkgconfig/llama.pc
nexa/__init__.py
nexa/cli/__init__.py
nexa/cli/entry.py
nexa/constants.py
nexa/general.py
nexa/gguf/__init__.py
nexa/gguf/lib/libggml_llama.dylib
nexa/gguf/lib/libllama.dylib
nexa/gguf/lib/libllava.dylib
nexa/gguf/lib/libstable-diffusion.dylib
nexa/gguf/lib_utils.py
nexa/gguf/llama/__init__.py
nexa/gguf/llama/_internals_transformers.py
nexa/gguf/llama/_logger_transformers.py
nexa/gguf/llama/_utils_transformers.py
nexa/gguf/llama/llama.py
nexa/gguf/llama/llama_cache.py
nexa/gguf/llama/llama_chat_format.py
nexa/gguf/llama/llama_cpp.py
nexa/gguf/llama/llama_grammar.py
nexa/gguf/llama/llama_speculative.py
nexa/gguf/llama/llama_tokenizer.py
nexa/gguf/llama/llama_types.py
nexa/gguf/llama/llava_cpp.py
nexa/gguf/nexa_inference_image.py
nexa/gguf/nexa_inference_text.py
nexa/gguf/nexa_inference_vlm.py
nexa/gguf/nexa_inference_voice.py
nexa/gguf/sd/__init__.py
nexa/gguf/sd/_internals_diffusion.py
nexa/gguf/sd/_logger_diffusion.py
nexa/gguf/sd/stable_diffusion.py
nexa/gguf/sd/stable_diffusion_cpp.py
nexa/gguf/server/__init__.py
nexa/gguf/server/nexa_service.py
nexa/gguf/streamlit/__init__.py
nexa/gguf/streamlit/streamlit_image_chat.py
nexa/gguf/streamlit/streamlit_text_chat.py
nexa/gguf/streamlit/streamlit_vlm.py
nexa/gguf/streamlit/streamlit_voice_chat.py
nexa/onnx/README.md
nexa/onnx/__init__.py
nexa/onnx/nexa_inference_image.py
nexa/onnx/nexa_inference_text.py
nexa/onnx/nexa_inference_tts.py
nexa/onnx/nexa_inference_voice.py
nexa/onnx/server/__init__.py
nexaai_metal-0.0.2.dist-info/METADATA
nexaai_metal-0.0.2.dist-info/WHEEL
nexaai_metal-0.0.2.dist-info/entry_points.txt
nexaai_metal-0.0.2.dist-info/licenses/LICENSE
nexaai_metal-0.0.2.dist-info/RECORD
