Metadata-Version: 2.1
Name: nexaai-metal
Version: 0.0.2
Summary: Nexa AI SDK
Author-Email: Nexa AI <octopus@nexa4ai.com>
License: MIT
Classifier: Programming Language :: Python :: 3
Classifier: Programming Language :: Python :: 3.9
Classifier: Programming Language :: Python :: 3.10
Classifier: Programming Language :: Python :: 3.11
Classifier: Programming Language :: Python :: 3.12
Project-URL: Homepage, https://github.com/NexaAI/nexaai-sdk-cpp
Project-URL: Issues, https://github.com/NexaAI/nexaai-sdk-cpp/issues
Project-URL: Documentation, https://docs-test.nexa4ai.com/
Requires-Dist: faster_whisper
Requires-Dist: typing-extensions>=4.5.0
Requires-Dist: numpy>=1.20.0
Requires-Dist: diskcache>=5.6.1
Requires-Dist: jinja2>=2.11.3
Requires-Dist: librosa>=0.8.0
Requires-Dist: boto3>=1.34.148
Requires-Dist: botocore>=1.34.148
Requires-Dist: fastapi
Requires-Dist: uvicorn
Requires-Dist: pydantic
Requires-Dist: pillow
Requires-Dist: prompt_toolkit
Requires-Dist: tqdm
Requires-Dist: importlib-metadata<7.0,>=1.4.0
Requires-Dist: tabulate
Requires-Dist: streamlit
Requires-Dist: librosa; extra == "onnx"
Requires-Dist: optimum[onnxruntime]>=1.7.3; extra == "onnx"
Requires-Dist: diffusers; extra == "onnx"
Requires-Dist: optuna; extra == "onnx"
Requires-Dist: pydantic; extra == "onnx"
Requires-Dist: PyYAML; extra == "onnx"
Requires-Dist: requests; extra == "onnx"
Requires-Dist: setuptools; extra == "onnx"
Requires-Dist: soundfile; extra == "onnx"
Requires-Dist: streamlit_audiorec; extra == "onnx"
Requires-Dist: transformers; extra == "onnx"
Requires-Dist: ttstokenizer; extra == "onnx"
Provides-Extra: onnx
